Metadata-Version: 2.1
Name: wagtail-2fa-new
Version: 1.8.0
Summary: Two factor authentication for Wagtail
Home-page: https://github.com/LabD/wagtail-2fa
Author: Lab Digital
Author-email: opensource@labdigital.nl
License: MIT
Classifier: Development Status :: 4 - Beta
Classifier: Environment :: Web Environment
Classifier: Framework :: Django
Classifier: Framework :: Django :: 3.2
Classifier: Framework :: Django :: 4.1
Classifier: Framework :: Django :: 4.2
Classifier: Framework :: Wagtail
Classifier: Framework :: Wagtail :: 2
Classifier: Framework :: Wagtail :: 3
Classifier: Framework :: Wagtail :: 4
Classifier: License :: OSI Approved :: MIT License
Classifier: Programming Language :: Python
Classifier: Programming Language :: Python :: 3.8
Classifier: Programming Language :: Python :: 3.9
Classifier: Programming Language :: Python :: 3.10
Classifier: Programming Language :: Python :: 3.11
Requires-Python: >=3.8
License-File: LICENSE
Requires-Dist: Django >=3.2
Requires-Dist: Wagtail >=4.1
Requires-Dist: django-otp >=0.8.1
Requires-Dist: six >=1.14.0
Requires-Dist: qrcode >=6.1
Provides-Extra: docs
Requires-Dist: sphinx >=1.4.1 ; extra == 'docs'
Requires-Dist: sphinx-rtd-theme >=0.4.3 ; extra == 'docs'
Provides-Extra: test
Requires-Dist: coverage ==5.5 ; extra == 'test'
Requires-Dist: pytest ==6.2.4 ; extra == 'test'
Requires-Dist: pytest-cov ==2.12.1 ; extra == 'test'
Requires-Dist: pytest-django ==4.4.0 ; extra == 'test'
Requires-Dist: flake8 ==3.9.2 ; extra == 'test'
Requires-Dist: isort ==5.9.3 ; extra == 'test'
Requires-Dist: flake8-blind-except ==0.2.0 ; extra == 'test'
Requires-Dist: flake8-debugger ==4.0.0 ; extra == 'test'
